game_development/__init__.py
game_development/_game_development.py
game_development/_game_mixer.py
game_development/_panda_utils.py
game_development/game_development.py
game_development-1.0.7.dist-info/LICENSE
game_development-1.0.7.dist-info/METADATA
game_development-1.0.7.dist-info/WHEEL
game_development-1.0.7.dist-info/top_level.txt
game_development-1.0.7.dist-info/RECORD
