Metadata-Version: 2.1
Name: game-development
Version: 1.0.7
Summary: Simplify 2D and 3D game development and combine the power of Panda3D and Pygame to create awesome games.
Home-page: https://github.com/MKM12345/game_development
Download-URL: https://pypi.org/project/game_development/
Author: MKM12345
Author-email: arekhon.shadow@gmail.com
License: MIT
Keywords: game development,pygame,panda3d
License-File: LICENSE
Requires-Dist: pygame
Requires-Dist: panda3d
